[
    {
        "id": 1,
        "data":"03/09/2011",
        "valor":"10",
        "credor":{
            "nome":"João",
            "senha":"123"
        },
        "devedor":{
            "nome":"Maria",
            "senha":"456"
        }
    },
    {
        "id": 2,
        "data":"04/09/2011",
        "valor":"12",
        "credor":{
            "nome":"Antonio",
            "senha":"789"
        },
        "devedor":{
            "nome":"Maria",
            "senha":"456"
        }
    },
    {
        "id": 3,
        "data":"04/09/2011",
        "valor":"5",
        "credor":{
            "nome":"Antonio",
            "senha":"789"
        },
        "devedor":{
            "nome":"José",
            "senha":"098"
        }
    },
    {
        "id": 4,
        "data":"05/09/2011",
        "valor":"3",
        "credor":{
            "nome":"Antonio",
            "senha":"789"
        },
        "devedor":{
            "nome":"Maria",
            "senha":"456"
        }
    },
    {
        "id": 5,
        "data":"05/09/2011",
        "valor":"18",
        "credor":{
            "nome":"João",
            "senha":"123"
        },
        "devedor":{
            "nome":"Maria",
            "senha":"456"
        }
    }
    
]